{
  "account": {
    "equity": 0.0,
    "margin_used": 0.0,
    "spot_usdc": 0.0
  },
  "total_balance": 0.0,
  "positions": [],
  "prices": {
    "SOL": 77.7955,
    "ETH": 1844.5,
    "HYPE": 26.1065,
    "BTC": 64219.5
  },
  "bot": {
    "version": "v6.0",
    "capital": 0,
    "total_pnl": 0.0,
    "strategy": "Williams %R + OBV v6.0 + EMA200 + Partial TP",
    "daily_trades": 0,
    "max_daily": 2,
    "weekly_trades": 0,
    "max_weekly": 6,
    "fear_greed": 8,
    "next_macro": "NFP 2026-03-06",
    "signals": {
      "SOL": {
        "price": 77.7365,
        "wr": -80.55847757483025,
        "rsi": 31.809815684565038,
        "ema200": 96.91653266722527,
        "trend": "BEAR",
        "signal": "WAIT",
        "reason": "W%R=-81 | OBV\u2193 | RSI=32"
      },
      "ETH": {
        "price": 1845.95,
        "wr": -80.60708263069141,
        "rsi": 32.77267026666135,
        "ema200": 2279.439541412067,
        "trend": "BEAR",
        "signal": "WAIT",
        "reason": "W%R=-81 | OBV\u2193 | RSI=33"
      },
      "HYPE": {
        "price": 26.1065,
        "wr": -88.33448833448836,
        "rsi": 26.617220272441955,
        "ema200": 29.297012172244514,
        "trend": "BEAR",
        "signal": "WAIT",
        "reason": "W%R=-88 | OBV\u2193 | RSI=27"
      }
    }
  },
  "recent_trades": [],
  "updated": "2026-02-24T01:55:01.239930+00:00"
}